mvk/__init__.py
mvk/hello.py
idrfabioss-0.0.1.dist-info/METADATA
idrfabioss-0.0.1.dist-info/WHEEL
idrfabioss-0.0.1.dist-info/top_level.txt
idrfabioss-0.0.1.dist-info/RECORD
